edda/__init__.py
edda/activity.py
edda/app.py
edda/channels.py
edda/compensation.py
edda/context.py
edda/exceptions.py
edda/hooks.py
edda/locking.py
edda/pydantic_utils.py
edda/replay.py
edda/retry.py
edda/workflow.py
edda/wsgi.py
edda/integrations/__init__.py
edda/integrations/graph/__init__.py
edda/integrations/graph/context.py
edda/integrations/graph/exceptions.py
edda/integrations/graph/graph.py
edda/integrations/graph/nodes.py
edda/integrations/llamaindex/__init__.py
edda/integrations/llamaindex/events.py
edda/integrations/llamaindex/exceptions.py
edda/integrations/llamaindex/workflow.py
edda/integrations/mcp/__init__.py
edda/integrations/mcp/decorators.py
edda/integrations/mcp/server.py
edda/integrations/mirascope/__init__.py
edda/integrations/mirascope/agent.py
edda/integrations/mirascope/call.py
edda/integrations/mirascope/decorator.py
edda/integrations/mirascope/types.py
edda/integrations/opentelemetry/__init__.py
edda/integrations/opentelemetry/hooks.py
edda/outbox/__init__.py
edda/outbox/relayer.py
edda/outbox/transactional.py
edda/serialization/__init__.py
edda/serialization/base.py
edda/serialization/json.py
edda/storage/__init__.py
edda/storage/migrations.py
edda/storage/models.py
edda/storage/notify_base.py
edda/storage/pg_notify.py
edda/storage/protocol.py
edda/storage/sqlalchemy_storage.py
edda/viewer_ui/__init__.py
edda/viewer_ui/app.py
edda/viewer_ui/components.py
edda/viewer_ui/data_service.py
edda/viewer_ui/theme.py
edda/visualizer/__init__.py
edda/visualizer/ast_analyzer.py
edda/visualizer/mermaid_generator.py
edda/migrations/mysql/20251217000000_initial_schema.sql
edda/migrations/postgresql/20251217000000_initial_schema.sql
edda/migrations/sqlite/20251217000000_initial_schema.sql
edda_framework-0.15.0.dist-info/METADATA
edda_framework-0.15.0.dist-info/WHEEL
edda_framework-0.15.0.dist-info/entry_points.txt
edda_framework-0.15.0.dist-info/licenses/LICENSE
edda_framework-0.15.0.dist-info/RECORD
