Metadata-Version: 2.4
Name: edda-framework
Version: 0.15.0
Summary: Lightweight Durable Execution Framework
Project-URL: Homepage, https://github.com/i2y/edda
Project-URL: Documentation, https://github.com/i2y/edda#readme
Project-URL: Repository, https://github.com/i2y/edda
Project-URL: Issues, https://github.com/i2y/edda/issues
Author-email: Yasushi Itoh <6240399+i2y@users.noreply.github.com>
License: MIT
License-File: LICENSE
Keywords: cloudevents,distributed,durable-execution,event-driven,knative,microservices,orchestration,workflow
Classifier: Development Status :: 3 - Alpha
Classifier: Intended Audience :: Developers
Classifier: License :: OSI Approved :: MIT License
Classifier: Programming Language :: Python :: 3.11
Classifier: Programming Language :: Python :: 3.12
Classifier: Programming Language :: Python :: 3.13
Classifier: Programming Language :: Python :: 3.14
Classifier: Topic :: Software Development :: Libraries :: Application Frameworks
Classifier: Topic :: System :: Distributed Computing
Requires-Python: >=3.11
Requires-Dist: a2wsgi>=1.10.0
Requires-Dist: aiosqlite>=0.21.0
Requires-Dist: anyio>=4.0.0
Requires-Dist: cloudevents>=1.12.0
Requires-Dist: httpx>=0.28.1
Requires-Dist: pydantic>=2.0.0
Requires-Dist: sqlalchemy[asyncio]>=2.0.0
Requires-Dist: uvloop>=0.22.1
Provides-Extra: cpu-monitor
Requires-Dist: psutil>=5.9.0; extra == 'cpu-monitor'
Provides-Extra: dev
Requires-Dist: black>=25.9.0; extra == 'dev'
Requires-Dist: mcp>=1.22.0; extra == 'dev'
Requires-Dist: mypy>=1.18.2; extra == 'dev'
Requires-Dist: pytest-asyncio>=1.2.0; extra == 'dev'
Requires-Dist: pytest-cov>=7.0.0; extra == 'dev'
Requires-Dist: pytest>=8.4.2; extra == 'dev'
Requires-Dist: ruff>=0.14.2; extra == 'dev'
Requires-Dist: starlette>=0.40.0; extra == 'dev'
Requires-Dist: testcontainers[mysql]>=4.0.0; extra == 'dev'
Requires-Dist: testcontainers[postgres]>=4.0.0; extra == 'dev'
Requires-Dist: tsuno>=0.1.3; extra == 'dev'
Provides-Extra: graph
Requires-Dist: pydantic-graph>=0.1.0; extra == 'graph'
Provides-Extra: llamaindex
Requires-Dist: llama-index-core>=0.12.0; extra == 'llamaindex'
Provides-Extra: mcp
Requires-Dist: mcp>=1.22.0; extra == 'mcp'
Provides-Extra: mirascope
Requires-Dist: mirascope[anthropic,google,openai]>=2.0.0a0; extra == 'mirascope'
Requires-Dist: pydantic-settings>=2.0.0; extra == 'mirascope'
Provides-Extra: mysql
Requires-Dist: aiomysql>=0.2.0; extra == 'mysql'
Provides-Extra: opentelemetry
Requires-Dist: opentelemetry-api>=1.20.0; extra == 'opentelemetry'
Requires-Dist: opentelemetry-exporter-otlp>=1.20.0; extra == 'opentelemetry'
Requires-Dist: opentelemetry-sdk>=1.20.0; extra == 'opentelemetry'
Provides-Extra: postgres-notify
Requires-Dist: asyncpg>=0.30.0; extra == 'postgres-notify'
Provides-Extra: postgresql
Requires-Dist: asyncpg>=0.30.0; extra == 'postgresql'
Provides-Extra: server
Requires-Dist: tsuno>=0.1.3; extra == 'server'
Provides-Extra: viewer
Requires-Dist: nicegui>=2.8.0; extra == 'viewer'
